vlcsync/__init__.py
vlcsync/cli.py
vlcsync/cli_utils.py
vlcsync/main.py
vlcsync/syncer.py
vlcsync/vlc.py
vlcsync/vlc_finder.py
vlcsync/vlc_socket.py
vlcsync/vlc_state.py
vlcsync-0.3.1.dist-info/entry_points.txt
vlcsync-0.3.1.dist-info/LICENSE.md
vlcsync-0.3.1.dist-info/WHEEL
vlcsync-0.3.1.dist-info/METADATA
vlcsync-0.3.1.dist-info/RECORD
