Metadata-Version: 2.1
Name: vlcsync
Version: 0.3.1
Summary: Utility for synchronize multiple instances of VLC. Supports seek, play and pause. 
Home-page: https://github.com/mrkeuz/vlcsync/
License: MIT
Author: mrkeuz
Author-email: mrkeuz@users.noreply.github.com
Requires-Python: >=3.8,<4.0
Classifier: Development Status :: 4 - Beta
Classifier: License :: OSI Approved :: MIT License
Classifier: Programming Language :: Python
Classifier: Programming Language :: Python :: 3
Classifier: Programming Language :: Python :: 3 :: Only
Classifier: Programming Language :: Python :: 3.10
Classifier: Programming Language :: Python :: 3.8
Classifier: Programming Language :: Python :: 3.9
Classifier: Topic :: Multimedia
Classifier: Topic :: Multimedia :: Video
Classifier: Topic :: Multimedia :: Video :: Display
Classifier: Topic :: Utilities
Requires-Dist: cached-property
Requires-Dist: click (>=8.1.3,<9.0.0)
Requires-Dist: loguru
Requires-Dist: psutil
Project-URL: Documentation, https://github.com/mrkeuz/vlcsync/
